MANIFEST.in
setup.cfg
setup.py
versioneer.py
bin/cronmon
cronmon/__init__.py
cronmon/_version.py
cronmon/cli.py
cronmon/log.py
cronmon/run.py
cronmon.egg-info/PKG-INFO
cronmon.egg-info/SOURCES.txt
cronmon.egg-info/dependency_links.txt
cronmon.egg-info/requires.txt
cronmon.egg-info/top_level.txt
cronmon/server/__init__.py