Metadata-Version: 1.1
Name: cronmon
Version: 0.2.1
Summary: Monitor your crontasks
Home-page: https://github.com/malev/cronmon
Author: Marcos Vanetta
Author-email: marcosvanetta@gmail.com
License: UNKNOWN
Platform: UNKNOWN
Classifier: Development Status :: 2 - Pre-Alpha
Classifier: Programming Language :: Python
Classifier: Programming Language :: Python :: 2
Classifier: Programming Language :: Python :: 2.7
Classifier: Programming Language :: Python :: 3
Classifier: Programming Language :: Python :: 3.4
